tests/__init__.py
tests/app.py
tests/test_lock.py
tests/test_mutex.py
zkcelery/__init__.py
zkcelery/backports.py
zkcelery/lock.py
zkcelery/mutex.py
zkcelery/scheduler.py
zkcelery-0.1.0.dist-info/DESCRIPTION.rst
zkcelery-0.1.0.dist-info/METADATA
zkcelery-0.1.0.dist-info/metadata.json
zkcelery-0.1.0.dist-info/RECORD
zkcelery-0.1.0.dist-info/top_level.txt
zkcelery-0.1.0.dist-info/WHEEL
